oscparser/__init__.py
oscparser/ctx.py
oscparser/decode.py
oscparser/encode.py
oscparser/framing/__init__.py
oscparser/framing/framer.py
oscparser/framing/fullframer.py
oscparser/framing/osc10.py
oscparser/framing/osc11.py
oscparser/processing/args/args.py
oscparser/processing/args/proccessing.py
oscparser/processing/osc/handlers.py
oscparser/processing/osc/processing.py
oscparser/types.py
oscparser-2.0.3.dist-info/METADATA
oscparser-2.0.3.dist-info/WHEEL
oscparser-2.0.3.dist-info/licenses/LICENSE
oscparser-2.0.3.dist-info/RECORD
