Metadata-Version: 2.4
Name: oscparser
Version: 2.0.3
Summary: Library for parsing and building Open Sound Control (OSC) messages and bundles.
License: MIT License
License-File: LICENSE
Keywords: osc,sound,midi,music
Author: Morph Tollon
Author-email: code@morphtollon.co.uk
Maintainer: Morph Tollon
Maintainer-email: code@morphtollon.co.uk
Requires-Python: >=3.13, <3.14
Classifier: Development Status :: 5 - Production/Stable
Classifier: Intended Audience :: Developers
Classifier: License :: Freely Distributable
Classifier: Programming Language :: Python :: 3
Classifier: Topic :: Multimedia :: Sound/Audio
Classifier: Topic :: System :: Networking
Requires-Dist: pydantic (>=2.12.5,<3.0.0)
Project-URL: Homepage, https://github.com/Theatre-Tools/python-osc-parser
Project-URL: Issues, https://github.com/Theatre-Tools/python-osc-parser/issues
Project-URL: Repository, https://github.com/Theatre-Tools/python-osc-parser
